{"timestamp": "2025-05-04T22:12:58.468954", "data": [{"NEWSID": "3ca00098-f879-4328-94e1-995fd75ffae7", "SCRIP_CD": 513436, "XML_NAME": "ANN_513436_3CA00098-F879-4328-94E1-995FD75FFAE7", "NEWSSUB": "Shah Alloys Ltd - 513436 - Results For The Financial Year Ended 31.03.2024", "DT_TM": "2024-05-30 16:01:13.637", "NEWS_DT": "2024-05-30T16:01:13.637", "CRITICALNEWS": 0, "ANNOUNCEMENT_TYPE": "A", "QUARTER_ID": null, "FILESTATUS": "N    ", "ATTACHMENTNAME": "eb2c8692-19b7-4749-8d0b-4eccb9c1f9ba.pdf", "MORE": "", "HEADLINE": "Results for the financial year ended 31.03.2024", "CATEGORYNAME": "Result", "OLD": 1, "RN": 1, "PDFFLAG": 1, "NSURL": "https://www.bseindia.com/stock-share-price/shah-alloys-ltd/shahalloys/513436/", "SLONGNAME": "Shah Alloys Ltd", "AGENDA_ID": 30, "TotalPageCnt": 82, "News_submission_dt": "2024-05-30T16:01:13", "DissemDT": "2024-05-30T16:01:13.637", "TimeDiff": "00:00:00", "Fld_Attachsize": 10687473, "SUBCATNAME": "Financial Results", "AUDIO_VIDEO_FILE": null}, {"NEWSID": "a544c8a7-656a-4a99-a4ae-cd917737bd2c", "SCRIP_CD": 540642, "XML_NAME": "ANN_540642_A544C8A7-656A-4A99-A4AE-CD917737BD2C", "NEWSSUB": "Salasar Techno Engineering Ltd - 540642 - Audited Financial Results For The Quarter/Year Ended 31St March 2024", "DT_TM": "2024-05-30 16:00:20.090", "NEWS_DT": "2024-05-30T16:00:20.09", "CRITICALNEWS": 0, "ANNOUNCEMENT_TYPE": "A", "QUARTER_ID": null, "FILESTATUS": "N    ", "ATTACHMENTNAME": "583bf960-fb15-42ce-850e-9ea0fa2b40d1.pdf", "MORE": "", "HEADLINE": "Please find enclosed herewith Audited Financial Results for Quarter & year ended 31.03.2024.", "CATEGORYNAME": "Result", "OLD": 1, "RN": 1, "PDFFLAG": 1, "NSURL": "https://www.bseindia.com/stock-share-price/salasar-techno-engineering-ltd/salasar/540642/", "SLONGNAME": "Salasar Techno Engineering Ltd", "AGENDA_ID": 30, "TotalPageCnt": 82, "News_submission_dt": "2024-05-30T16:00:19", "DissemDT": "2024-05-30T16:00:20.09", "TimeDiff": "00:00:01", "Fld_Attachsize": 3576778, "SUBCATNAME": "Financial Results", "AUDIO_VIDEO_FILE": null}, {"NEWSID": "4c089159-8d3c-4aa2-9f6c-15aad078dac9", "SCRIP_CD": 507872, "XML_NAME": "ANN_507872_4C089159-8D3C-4AA2-9F6C-15AAD078DAC9", "NEWSSUB": "Ashnoor Textile Mills Ltd - 507872 - Results-Audited Financial Results For The Financial Year Ended March 31, 2024", "DT_TM": "2024-05-30 15:59:36.797", "NEWS_DT": "2024-05-30T15:59:36.797", "CRITICALNEWS": 0, "ANNOUNCEMENT_TYPE": "A", "QUARTER_ID": null, "FILESTATUS": "N    ", "ATTACHMENTNAME": "9191e724-afea-411e-9373-081c28929bba.pdf", "MORE": "", "HEADLINE": "Financial Results for the financial year ended March 31, 2024, along with a Limited Audit Review Report (Audited) and a declaration under Regulation 33(3)(d) of LODR are attached.", "CATEGORYNAME": "Result", "OLD": 1, "RN": 1, "PDFFLAG": 1, "NSURL": "https://www.bseindia.com/stock-share-price/ashnoor-textile-mills-ltd/ashnoor/507872/", "SLONGNAME": "Ashnoor Textile Mills Ltd", "AGENDA_ID": 30, "TotalPageCnt": 82, "News_submission_dt": "2024-05-30T15:59:36", "DissemDT": "2024-05-30T15:59:36.797", "TimeDiff": "00:00:00", "Fld_Attachsize": 3019760, "SUBCATNAME": "Financial Results", "AUDIO_VIDEO_FILE": null}, {"NEWSID": "4988a47c-f82b-4f8d-b316-eccbbc239ade", "SCRIP_CD": 532617, "XML_NAME": "ANN_532617_4988A47C-F82B-4F8D-B316-ECCBBC239ADE", "NEWSSUB": "Jet Airways (India) Ltd - 532617 - Results-Delay in Financial Results", "DT_TM": "2024-05-30 15:59:22.040", "NEWS_DT": "2024-05-30T15:59:22.04", "CRITICALNEWS": 0, "ANNOUNCEMENT_TYPE": "A", "QUARTER_ID": null, "FILESTATUS": "N    ", "ATTACHMENTNAME": "511cd259-c5d5-408c-aa16-31ec8a8a1650.pdf", "MORE": "Dear Sir / Madam,\r\n\r\nPlease find attached the detailed reason for delay in submission of financial results for the quarter and year ended 31.03.2024.\r\n\r\nKindly take the same on your record.\r\n\r\nThank you\r\nWith kind regards,\r\nCS Jaspreet Singh\r\nCompany Secretary and Compliance Officer", "HEADLINE": "Dear Sir / Madam,\r\n\r\nPlease find attached the detailed reason for delay in submission of financial results for the quarter and year ended 31.03.2024.\r\n\r\nKindly take the same on your record.\r\n\r\nThank ....", "CATEGORYNAME": "Result", "OLD": 1, "RN": 1, "PDFFLAG": 1, "NSURL": "https://www.bseindia.com/stock-share-price/jet-airways-(india)-ltd/jetairways/532617/", "SLONGNAME": "Jet Airways (India) Ltd", "AGENDA_ID": 30, "TotalPageCnt": 82, "News_submission_dt": "2024-05-30T15:59:21", "DissemDT": "2024-05-30T15:59:22.043", "TimeDiff": "00:00:01", "Fld_Attachsize": 760526, "SUBCATNAME": "Financial Results", "AUDIO_VIDEO_FILE": null}, {"NEWSID": "c73dc7fc-f0aa-4256-8742-83171c8d4039", "SCRIP_CD": 539043, "XML_NAME": "ANN_539043_C73DC7FC-F0AA-4256-8742-83171C8D4039", "NEWSSUB": "BKM Industries Ltd - 539043 - Audited Financial Results For The Quarter And Year Ended 31.03.2024", "DT_TM": "2024-05-30 15:58:52.510", "NEWS_DT": "2024-05-30T15:58:52.51", "CRITICALNEWS": 0, "ANNOUNCEMENT_TYPE": "A", "QUARTER_ID": null, "FILESTATUS": "N    ", "ATTACHMENTNAME": "a22f1b1f-8907-4103-9b1c-5123660b0c8d.pdf", "MORE": "", "HEADLINE": "Audited Financial Results for the Quarter and year ended 31.03.2024", "CATEGORYNAME": "Result", "OLD": 1, "RN": 1, "PDFFLAG": 1, "NSURL": "https://www.bseindia.com/stock-share-price/bkm-industries-ltd/bkmindst/539043/", "SLONGNAME": "BKM Industries Ltd", "AGENDA_ID": 30, "TotalPageCnt": 82, "News_submission_dt": "2024-05-30T15:58:52", "DissemDT": "2024-05-30T15:58:52.51", "TimeDiff": "00:00:00", "Fld_Attachsize": 21123864, "SUBCATNAME": "Financial Results", "AUDIO_VIDEO_FILE": null}, {"NEWSID": "5ad2d700-79bf-428e-826b-873bb7de8af6", "SCRIP_CD": 531065, "XML_NAME": "ANN_531065_5AD2D700-79BF-428E-826B-873BB7DE8AF6", "NEWSSUB": "Oswal Overseas Ltd - 531065 - Standalone Audited Financial Results, Audit Report For The Quarter And Year Ended On March 31, 2024", "DT_TM": "2024-05-30 15:58:21.117", "NEWS_DT": "2024-05-30T15:58:21.117", "CRITICALNEWS": 0, "ANNOUNCEMENT_TYPE": "A", "QUARTER_ID": null, "FILESTATUS": "N    ", "ATTACHMENTNAME": "47e143a7-1d9e-40ff-903a-6fbd05bf316e.pdf", "MORE": "", "HEADLINE": "Standalone Audited Financial Results for the quarter and year ended on March 31, 2024 along with Audit report on the same and declaration under regulation 33(3)(d) of the SEBI (LODR) Regulation, 2015", "CATEGORYNAME": "Result", "OLD": 1, "RN": 1, "PDFFLAG": 1, "NSURL": "https://www.bseindia.com/stock-share-price/oswal-overseas-ltd/oswalor/531065/", "SLONGNAME": "Oswal Overseas Ltd", "AGENDA_ID": 30, "TotalPageCnt": 82, "News_submission_dt": "2024-05-30T15:58:20", "DissemDT": "2024-05-30T15:58:21.117", "TimeDiff": "00:00:01", "Fld_Attachsize": 7759949, "SUBCATNAME": "Financial Results", "AUDIO_VIDEO_FILE": null}, {"NEWSID": "4b62ecbc-5469-4763-9fd4-2485d107329b", "SCRIP_CD": 524037, "XML_NAME": "ANN_524037_4B62ECBC-5469-4763-9FD4-2485D107329B", "NEWSSUB": "Rama Phosphates Ltd - 524037 - Audited Financial Results For The Quarter And Year Ended March 31, 2024 Along With Auditor''s Report", "DT_TM": "2024-05-30 15:56:38.503", "NEWS_DT": "2024-05-30T15:56:38.503", "CRITICALNEWS": 0, "ANNOUNCEMENT_TYPE": "A", "QUARTER_ID": null, "FILESTATUS": "N    ", "ATTACHMENTNAME": "7fd92229-fb67-4df6-b60e-5cb810a85067.pdf", "MORE": "", "HEADLINE": "Audited Financial Results for the quarter and year ended March 31, 2024 along with Auditor''s Report", "CATEGORYNAME": "Result", "OLD": 1, "RN": 1, "PDFFLAG": 1, "NSURL": "https://www.bseindia.com/stock-share-price/rama-phosphates-ltd/ramapho/524037/", "SLONGNAME": "Rama Phosphates Ltd", "AGENDA_ID": 30, "TotalPageCnt": 82, "News_submission_dt": "2024-05-30T15:56:38", "DissemDT": "2024-05-30T15:56:38.503", "TimeDiff": "00:00:00", "Fld_Attachsize": 8199590, "SUBCATNAME": "Financial Results", "AUDIO_VIDEO_FILE": null}, {"NEWSID": "d6258341-dfff-4bff-8c81-0e34f09fe382", "SCRIP_CD": 514400, "XML_NAME": "ANN_514400_D6258341-DFFF-4BFF-8C81-0E34F09FE382", "NEWSSUB": "Garware Synthetics Ltd - 514400 - Submission Of Audited Financial Results For The Quarter And Year Ended 31.03.2024.", "DT_TM": "2024-05-30 15:56:13.227", "NEWS_DT": "2024-05-30T15:56:13.227", "CRITICALNEWS": 0, "ANNOUNCEMENT_TYPE": "A", "QUARTER_ID": null, "FILESTATUS": "N    ", "ATTACHMENTNAME": "a486d548-1c50-4c91-b7e4-ef0480545ae9.pdf", "MORE": "", "HEADLINE": "Submission of Audited Financial Results for the Quarter and Year ended 31.03.2024.", "CATEGORYNAME": "Result", "OLD": 1, "RN": 1, "PDFFLAG": 1, "NSURL": "https://www.bseindia.com/stock-share-price/garware-synthetics-ltd/garwsyn/514400/", "SLONGNAME": "Garware Synthetics Ltd", "AGENDA_ID": 30, "TotalPageCnt": 82, "News_submission_dt": "2024-05-30T15:56:13", "DissemDT": "2024-05-30T15:56:13.227", "TimeDiff": "00:00:00", "Fld_Attachsize": 7400330, "SUBCATNAME": "Financial Results", "AUDIO_VIDEO_FILE": null}, {"NEWSID": "4007e2ee-d5dc-4e78-959f-ccd5da55b3c4", "SCRIP_CD": 532719, "XML_NAME": "ANN_532719_4007E2EE-D5DC-4E78-959F-CCD5DA55B3C4", "NEWSSUB": "B. L. Kashyap and Sons Ltd - 532719 - Audited Financial Results For The Quarter And Year Ended March 31, 2024", "DT_TM": "2024-05-30 15:55:22.650", "NEWS_DT": "2024-05-30T15:55:22.65", "CRITICALNEWS": 0, "ANNOUNCEMENT_TYPE": "A", "QUARTER_ID": null, "FILESTATUS": "N    ", "ATTACHMENTNAME": "f781002b-d064-4f87-a394-82117ea4f930.pdf", "MORE": "", "HEADLINE": "Approved audited standalone & consolidated financial results for the quarter and year ended March 31, 2024", "CATEGORYNAME": "Result", "OLD": 1, "RN": 1, "PDFFLAG": 1, "NSURL": "https://www.bseindia.com/stock-share-price/b-l-kashyap-and-sons-ltd/blkashyap/532719/", "SLONGNAME": "B. L. Kashyap and Sons Ltd", "AGENDA_ID": 30, "TotalPageCnt": 82, "News_submission_dt": "2024-05-30T15:55:22", "DissemDT": "2024-05-30T15:55:22.65", "TimeDiff": "00:00:00", "Fld_Attachsize": 7964284, "SUBCATNAME": "Financial Results", "AUDIO_VIDEO_FILE": null}, {"NEWSID": "32cebda2-df87-4f8a-b88f-38dc0bbd3d2b", "SCRIP_CD": 531541, "XML_NAME": "ANN_531541_32CEBDA2-DF87-4F8A-B88F-38DC0BBD3D2B", "NEWSSUB": "Kobo Biotech Ltd-$ - 531541 - Audited Financial Results For The Quarter And Year Ended 31St March, 2024.", "DT_TM": "2024-05-30 15:55:22.290", "NEWS_DT": "2024-05-30T15:55:22.29", "CRITICALNEWS": 0, "ANNOUNCEMENT_TYPE": "A", "QUARTER_ID": null, "FILESTATUS": "N    ", "ATTACHMENTNAME": "b4befa81-638f-4e3d-8442-ed8fd8f88f6e.pdf", "MORE": "", "HEADLINE": "Submission of Audited Financial Results along with the Auditors Report thereon for the auarter and the year ended 31st March, 2024", "CATEGORYNAME": "Result", "OLD": 1, "RN": 1, "PDFFLAG": 1, "NSURL": "https://www.bseindia.com/stock-share-price/kobo-biotech-ltd/kobo/531541/", "SLONGNAME": "Kobo Biotech Ltd-$", "AGENDA_ID": 30, "TotalPageCnt": 82, "News_submission_dt": "2024-05-30T15:55:22", "DissemDT": "2024-05-30T15:55:22.29", "TimeDiff": "00:00:00", "Fld_Attachsize": 998173, "SUBCATNAME": "Financial Results", "AUDIO_VIDEO_FILE": null}, {"NEWSID": "0f95f639-948a-40ce-bb3e-d5b16418e965", "SCRIP_CD": 532139, "XML_NAME": "ANN_532139_0F95F639-948A-40CE-BB3E-D5B16418E965", "NEWSSUB": "G-Tech Info-Training Ltd - 532139 - Audited Financial Results Of The Company For The Year Ended 31St March, 2024", "DT_TM": "2024-05-30 15:53:33.793", "NEWS_DT": "2024-05-30T15:53:33.793", "CRITICALNEWS": 0, "ANNOUNCEMENT_TYPE": "A", "QUARTER_ID": null, "FILESTATUS": "N    ", "ATTACHMENTNAME": "5eb8189b-3cd6-4d51-b07d-76dbe709b1ee.pdf", "MORE": "", "HEADLINE": "Audited Financial Results of the company for the year ended 31st March, 2024", "CATEGORYNAME": "Result", "OLD": 1, "RN": 1, "PDFFLAG": 1, "NSURL": "https://www.bseindia.com/stock-share-price/g-tech-info-training-ltd/gteit/532139/", "SLONGNAME": "G-Tech Info-Training Ltd", "AGENDA_ID": 30, "TotalPageCnt": 82, "News_submission_dt": "2024-05-30T15:53:33", "DissemDT": "2024-05-30T15:53:33.793", "TimeDiff": "00:00:00", "Fld_Attachsize": 9068846, "SUBCATNAME": "Financial Results", "AUDIO_VIDEO_FILE": null}, {"NEWSID": "1927f0cc-88ed-4577-a25b-c2f0381a1169", "SCRIP_CD": 531928, "XML_NAME": "ANN_531928_1927F0CC-88ED-4577-A25B-C2F0381A1169", "NEWSSUB": "Golden Carpets Ltd - 531928 - Audited Financial Results As Per Regulation 33 & 30 Of SEBI (Listing Obligations And Disclosures Requirement) 2015.", "DT_TM": "2024-05-30 15:53:27.600", "NEWS_DT": "2024-05-30T15:53:27.6", "CRITICALNEWS": 0, "ANNOUNCEMENT_TYPE": "A", "QUARTER_ID": null, "FILESTATUS": "N    ", "ATTACHMENTNAME": "b3aea06c-5bc4-47a4-89a2-d58c79f2a6f4.pdf", "MORE": "", "HEADLINE": "The Board of Directors have considered and approved audited financial results for the quarter ad financial year ended 31.03.2024 and taken note of audit report with unmodified opinion", "CATEGORYNAME": "Result", "OLD": 1, "RN": 1, "PDFFLAG": 1, "NSURL": "https://www.bseindia.com/stock-share-price/golden-carpets-ltd/golca/531928/", "SLONGNAME": "Golden Carpets Ltd", "AGENDA_ID": 30, "TotalPageCnt": 82, "News_submission_dt": "2024-05-30T15:53:27", "DissemDT": "2024-05-30T15:53:27.6", "TimeDiff": "00:00:00", "Fld_Attachsize": 5947582, "SUBCATNAME": "Financial Results", "AUDIO_VIDEO_FILE": null}, {"NEWSID": "08a89c08-61f3-47a4-9013-4ee1a5b36acf", "SCRIP_CD": 531716, "XML_NAME": "ANN_531716_08A89C08-61F3-47A4-9013-4EE1A5B36ACF", "NEWSSUB": "Tricom Fruit Products Ltd - 531716 - Results-Financial Results For The Quarter And Year Ended March 31,2024", "DT_TM": "2024-05-30 15:52:55.480", "NEWS_DT": "2024-05-30T15:52:55.48", "CRITICALNEWS": 0, "ANNOUNCEMENT_TYPE": "A", "QUARTER_ID": null, "FILESTATUS": "N    ", "ATTACHMENTNAME": "20e97af8-bac2-40b2-9d29-ea6c69765b9d.pdf", "MORE": "Board of Director in its meeting held today i.e. 30th May,2024 interalia considered and approved the Audited Financial Results of the Company for the Quarter and year ended on 31st March,2024. enclosed herewith please find following:\r\n1. Audited Financial Results of the Company for the quarter and year ended on 31st March,2024 along with the statement of Assets and Liabilities and Cash Flow Statement for the year ended 31st March,2024.\r\n2. Auditors Report on Audited Financial Results for the Quarter and Year ended March 31,2024 \r\n3.Declaration regarding Unmodified Opinion.", "HEADLINE": "Board of Director in its meeting held today i.e. 30th May,2024 interalia considered and approved the Audited Financial Results of the Company for the Quarter and year ended on 31st March,2024. ....", "CATEGORYNAME": "Result", "OLD": 1, "RN": 1, "PDFFLAG": 1, "NSURL": "https://www.bseindia.com/stock-share-price/tricom-fruit-products-ltd/tricomfru/531716/", "SLONGNAME": "Tricom Fruit Products Ltd", "AGENDA_ID": 30, "TotalPageCnt": 82, "News_submission_dt": "2024-05-30T15:52:55", "DissemDT": "2024-05-30T15:52:55.48", "TimeDiff": "00:00:00", "Fld_Attachsize": 19361427, "SUBCATNAME": "Financial Results", "AUDIO_VIDEO_FILE": null}, {"NEWSID": "f6b13b2d-577f-4cb9-bd3b-9d42a32318cd", "SCRIP_CD": 512597, "XML_NAME": "ANN_512597_F6B13B2D-577F-4CB9-BD3B-9D42A32318CD", "NEWSSUB": "Keynote Financial Services Ltd - 512597 - Audited Financial Results (Standalone And Consolidated) For The Quarter And Financial Year Ended On March 31, 2024", "DT_TM": "2024-05-30 15:52:33.040", "NEWS_DT": "2024-05-30T15:52:33.04", "CRITICALNEWS": 0, "ANNOUNCEMENT_TYPE": "A", "QUARTER_ID": null, "FILESTATUS": "N    ", "ATTACHMENTNAME": "4ba30f0c-f010-4520-aa58-9081b4358403.pdf", "MORE": "", "HEADLINE": "Audited Financial Results (Standalone and Consolidated) for the quarter and finacial year ended on March 31, 2024", "CATEGORYNAME": "Result", "OLD": 1, "RN": 1, "PDFFLAG": 1, "NSURL": "https://www.bseindia.com/stock-share-price/keynote-financial-services-ltd/keyfinserv/512597/", "SLONGNAME": "Keynote Financial Services Ltd", "AGENDA_ID": 30, "TotalPageCnt": 82, "News_submission_dt": "2024-05-30T15:52:32", "DissemDT": "2024-05-30T15:52:33.043", "TimeDiff": "00:00:01", "Fld_Attachsize": 5848696, "SUBCATNAME": "Financial Results", "AUDIO_VIDEO_FILE": null}, {"NEWSID": "74e4efbd-1b10-4a33-8d24-89a674bee621", "SCRIP_CD": 532914, "XML_NAME": "ANN_532914_74E4EFBD-1B10-4A33-8D24-89A674BEE621", "NEWSSUB": "Arcotech Ltd - 532914 - Audited Results For FY 2023-24", "DT_TM": "2024-05-30 15:51:09.930", "NEWS_DT": "2024-05-30T15:51:09.93", "CRITICALNEWS": 0, "ANNOUNCEMENT_TYPE": "A", "QUARTER_ID": null, "FILESTATUS": "N    ", "ATTACHMENTNAME": "0efeba2c-1920-4a82-916a-ad55b067898d.pdf", "MORE": "", "HEADLINE": "Audited Financial Results for the FY 2023-24", "CATEGORYNAME": "Result", "OLD": 1, "RN": 1, "PDFFLAG": 1, "NSURL": "https://www.bseindia.com/stock-share-price/arcotech-ltd/arcotech/532914/", "SLONGNAME": "Arcotech Ltd", "AGENDA_ID": 30, "TotalPageCnt": 82, "News_submission_dt": "2024-05-30T15:51:09", "DissemDT": "2024-05-30T15:51:09.93", "TimeDiff": "00:00:00", "Fld_Attachsize": 1407784, "SUBCATNAME": "Financial Results", "AUDIO_VIDEO_FILE": null}, {"NEWSID": "8e37f14f-c835-4f66-8677-6acea6e4aec1", "SCRIP_CD": 533104, "XML_NAME": "ANN_533104_8E37F14F-C835-4F66-8677-6ACEA6E4AEC1", "NEWSSUB": "Globus Spirits Ltd - 533104 - Results", "DT_TM": "2024-05-30 15:50:55.283", "NEWS_DT": "2024-05-30T15:50:55.283", "CRITICALNEWS": 0, "ANNOUNCEMENT_TYPE": "A", "QUARTER_ID": null, "FILESTATUS": "N    ", "ATTACHMENTNAME": "3375de7e-7eb1-4d8e-b0ee-e3b83e9cbf35.pdf", "MORE": "", "HEADLINE": "Results", "CATEGORYNAME": "Result", "OLD": 1, "RN": 1, "PDFFLAG": 1, "NSURL": "https://www.bseindia.com/stock-share-price/globus-spirits-ltd/globusspr/533104/", "SLONGNAME": "Globus Spirits Ltd", "AGENDA_ID": 30, "TotalPageCnt": 82, "News_submission_dt": "2024-05-30T15:50:55", "DissemDT": "2024-05-30T15:50:55.283", "TimeDiff": "00:00:00", "Fld_Attachsize": 1989843, "SUBCATNAME": "Financial Results", "AUDIO_VIDEO_FILE": null}, {"NEWSID": "cafd39dc-ae46-4799-b323-7c0c73f8b2b2", "SCRIP_CD": 541143, "XML_NAME": "ANN_541143_CAFD39DC-AE46-4799-B323-7C0C73F8B2B2", "NEWSSUB": "Bharat Dynamics Ltd - 541143 - Audited Financial Results For The Quarter And Year 31.03.204", "DT_TM": "2024-05-30 15:50:54.913", "NEWS_DT": "2024-05-30T15:50:54.913", "CRITICALNEWS": 0, "ANNOUNCEMENT_TYPE": "A", "QUARTER_ID": null, "FILESTATUS": "N    ", "ATTACHMENTNAME": "1b7e8635-dabc-42d4-a42c-c92066b0d3c4.pdf", "MORE": "", "HEADLINE": "Audited Financial results for the quarter and year 31.03.2024", "CATEGORYNAME": "Result", "OLD": 1, "RN": 1, "PDFFLAG": 1, "NSURL": "https://www.bseindia.com/stock-share-price/bharat-dynamics-ltd/bdl/541143/", "SLONGNAME": "Bharat Dynamics Ltd", "AGENDA_ID": 30, "TotalPageCnt": 82, "News_submission_dt": "2024-05-30T15:50:54", "DissemDT": "2024-05-30T15:50:54.913", "TimeDiff": "00:00:00", "Fld_Attachsize": 11644590, "SUBCATNAME": "Financial Results", "AUDIO_VIDEO_FILE": null}, {"NEWSID": "e7f21701-9478-4c80-89e7-f3e78fb0179c", "SCRIP_CD": 531203, "XML_NAME": "ANN_531203_E7F21701-9478-4C80-89E7-F3E78FB0179C", "NEWSSUB": "Tradewell Holdings Ltd - 531203 - AUDITED STANDALONE FINANCIAL RESULTS OF THE COMPANY FOR THE FOURTH QUARTER AND YEAR ENDED 31ST MARCH, 2024 AS PER THE REGULATIONS 33 OF SEBI (LISTING OBLIGATIONS & DISCLOSURE REQUIREMENTS) REGULATIONS, 2015", "DT_TM": "2024-05-30 15:50:11.267", "NEWS_DT": "2024-05-30T15:50:11.267", "CRITICALNEWS": 0, "ANNOUNCEMENT_TYPE": "A", "QUARTER_ID": null, "FILESTATUS": "N    ", "ATTACHMENTNAME": "a8ea2627-f432-4d1c-a4b8-0f34dff0b958.pdf", "MORE": "", "HEADLINE": "SUBMISSION OF AUDITED RESULTS FOR THE YEAR ENDED ON 31.03.2024", "CATEGORYNAME": "Result", "OLD": 1, "RN": 1, "PDFFLAG": 1, "NSURL": "https://www.bseindia.com/stock-share-price/tradewell-holdings-ltd/tradewell/531203/", "SLONGNAME": "Tradewell Holdings Ltd", "AGENDA_ID": 30, "TotalPageCnt": 82, "News_submission_dt": "2024-05-30T15:50:11", "DissemDT": "2024-05-30T15:50:11.267", "TimeDiff": "00:00:00", "Fld_Attachsize": 4288313, "SUBCATNAME": "Financial Results", "AUDIO_VIDEO_FILE": null}, {"NEWSID": "49b98761-753a-4ef1-9f4e-aa4aeb5d618f", "SCRIP_CD": 512589, "XML_NAME": "ANN_512589_49B98761-753A-4EF1-9F4E-AA4AEB5D618F", "NEWSSUB": "Sita Enterprises Ltd - 512589 - Audited Financial Results For The Fourth Quarter And Financial Year Ended March 31, 2024.", "DT_TM": "2024-05-30 15:49:20.267", "NEWS_DT": "2024-05-30T15:49:20.267", "CRITICALNEWS": 0, "ANNOUNCEMENT_TYPE": "A", "QUARTER_ID": null, "FILESTATUS": "N    ", "ATTACHMENTNAME": "081b364d-3f05-40c2-abb6-36755d9dd11c.pdf", "MORE": "", "HEADLINE": "Audited Financial Results for the Forth Quarter and Financial Year ended March 31, 2024", "CATEGORYNAME": "Result", "OLD": 1, "RN": 1, "PDFFLAG": 1, "NSURL": "https://www.bseindia.com/stock-share-price/sita-enterprises-ltd/sitaent/512589/", "SLONGNAME": "Sita Enterprises Ltd", "AGENDA_ID": 30, "TotalPageCnt": 82, "News_submission_dt": "2024-05-30T15:49:20", "DissemDT": "2024-05-30T15:49:20.267", "TimeDiff": "00:00:00", "Fld_Attachsize": 1879203, "SUBCATNAME": "Financial Results", "AUDIO_VIDEO_FILE": null}, {"NEWSID": "b134a674-5a02-48cf-8c29-86c8bf7c0b31", "SCRIP_CD": 530795, "XML_NAME": "ANN_530795_B134A674-5A02-48CF-8C29-86C8BF7C0B31", "NEWSSUB": "Suncity Synthetics Ltd - 530795 - Financial Results For 31St March, 2024", "DT_TM": "2024-05-30 15:49:01.150", "NEWS_DT": "2024-05-30T15:49:01.15", "CRITICALNEWS": 0, "ANNOUNCEMENT_TYPE": "A", "QUARTER_ID": null, "FILESTATUS": "N    ", "ATTACHMENTNAME": "2d4811b9-9175-4698-ba43-7826ca006b84.pdf", "MORE": "", "HEADLINE": "Submission of Audited Financial Results for 31st March, 2024", "CATEGORYNAME": "Result", "OLD": 1, "RN": 1, "PDFFLAG": 1, "NSURL": "https://www.bseindia.com/stock-share-price/suncity-synthetics-ltd/suncitysy/530795/", "SLONGNAME": "Suncity Synthetics Ltd", "AGENDA_ID": 30, "TotalPageCnt": 82, "News_submission_dt": "2024-05-30T15:49:01", "DissemDT": "2024-05-30T15:49:01.15", "TimeDiff": "00:00:00", "Fld_Attachsize": 3500959, "SUBCATNAME": "Financial Results", "AUDIO_VIDEO_FILE": null}, {"NEWSID": "eaec4c95-6789-4926-ac6d-b03ee2c4b4e7", "SCRIP_CD": 526225, "XML_NAME": "ANN_526225_EAEC4C95-6789-4926-AC6D-B03EE2C4B4E7", "NEWSSUB": "Bloom Dekor Ltd-$ - 526225 - Financial Results For The Quarter And Year Ended 31/03/2024", "DT_TM": "2024-05-30 15:48:44.593", "NEWS_DT": "2024-05-30T15:48:44.593", "CRITICALNEWS": 0, "ANNOUNCEMENT_TYPE": "A", "QUARTER_ID": null, "FILESTATUS": "N    ", "ATTACHMENTNAME": "5a67a3bd-1e24-4036-a224-d8d16453903a.pdf", "MORE": "", "HEADLINE": "Financial results for the quarter and year ended 31/03/2024 approved by Board of Directors in their meeting held on 30/05/2024", "CATEGORYNAME": "Result", "OLD": 1, "RN": 1, "PDFFLAG": 1, "NSURL": "https://www.bseindia.com/stock-share-price/bloom-dekor-ltd/bloom/526225/", "SLONGNAME": "Bloom Dekor Ltd-$", "AGENDA_ID": 30, "TotalPageCnt": 82, "News_submission_dt": "2024-05-30T15:48:44", "DissemDT": "2024-05-30T15:48:44.593", "TimeDiff": "00:00:00", "Fld_Attachsize": 7316326, "SUBCATNAME": "Financial Results", "AUDIO_VIDEO_FILE": null}, {"NEWSID": "e6c15333-a096-44db-be6c-ce8b878744df", "SCRIP_CD": 540125, "XML_NAME": "ANN_540125_E6C15333-A096-44DB-BE6C-CE8B878744DF", "NEWSSUB": "Radhika Jeweltech Ltd - 540125 - Outcome Of Meeting Of Board Of Directors Dated 30Th May, 2024", "DT_TM": "2024-05-30 15:47:42.007", "NEWS_DT": "2024-05-30T15:47:42.007", "CRITICALNEWS": 0, "ANNOUNCEMENT_TYPE": "A", "QUARTER_ID": null, "FILESTATUS": "N    ", "ATTACHMENTNAME": "16e3d08f-7349-4ed0-a514-e5d5201f0cb7.pdf", "MORE": "", "HEADLINE": "Financial Result for the year ended on 31.03.2024", "CATEGORYNAME": "Result", "OLD": 1, "RN": 1, "PDFFLAG": 1, "NSURL": "https://www.bseindia.com/stock-share-price/radhika-jeweltech-ltd/radhikajwe/540125/", "SLONGNAME": "Radhika Jeweltech Ltd", "AGENDA_ID": 30, "TotalPageCnt": 82, "News_submission_dt": "2024-05-30T15:47:41", "DissemDT": "2024-05-30T15:47:42.007", "TimeDiff": "00:00:01", "Fld_Attachsize": 11606271, "SUBCATNAME": "Financial Results", "AUDIO_VIDEO_FILE": null}, {"NEWSID": "fa05d786-98b0-4f1c-852e-caa5178cb7e2", "SCRIP_CD": 532392, "XML_NAME": "ANN_532392_FA05D786-98B0-4F1C-852E-CAA5178CB7E2", "NEWSSUB": "Creative Eye Ltd - 532392 - Standalone Audited Financial Results Of The Company For The Fourth Quarter And Financial Year Ended 31St March, 2024  Along With Statement Of Assets And Liabilities And Cash Flow Statement  For The Year Ended 31St March, 2024", "DT_TM": "2024-05-30 15:47:36.323", "NEWS_DT": "2024-05-30T15:47:36.323", "CRITICALNEWS": 0, "ANNOUNCEMENT_TYPE": "A", "QUARTER_ID": null, "FILESTATUS": "N    ", "ATTACHMENTNAME": "783941d8-114a-4c4c-a44c-cb52e908bdb0.pdf", "MORE": "This is to inform you that Board of Directors at their meeting held today i.e. Thursday, 30th May,2024 commenced at 11.30 A.M. and concluded at 3.20 P.M. inter-alia considered and approved the attached matters.", "HEADLINE": "This is to inform you that Board of Directors at their meeting held today i.e. Thursday, 30th May,2024 commenced at 11.30 A.M. and concluded at 3.20 P.M. inter-alia considered and approved ....", "CATEGORYNAME": "Result", "OLD": 1, "RN": 1, "PDFFLAG": 1, "NSURL": "https://www.bseindia.com/stock-share-price/creative-eye-ltd/creativeye/532392/", "SLONGNAME": "Creative Eye Ltd", "AGENDA_ID": 30, "TotalPageCnt": 82, "News_submission_dt": "2024-05-30T15:47:36", "DissemDT": "2024-05-30T15:47:36.323", "TimeDiff": "00:00:00", "Fld_Attachsize": 8108063, "SUBCATNAME": "Financial Results", "AUDIO_VIDEO_FILE": null}, {"NEWSID": "63bd34ea-8bde-41e0-a124-d582d44c07f0", "SCRIP_CD": 509870, "XML_NAME": "ANN_509870_63BD34EA-8BDE-41E0-A124-D582D44C07F0", "NEWSSUB": "Shah Construction Company Ltd - 509870 - Audited Financial Results For Quarter And Year Ended On 31St March, 2024", "DT_TM": "2024-05-30 15:47:23.590", "NEWS_DT": "2024-05-30T15:47:23.59", "CRITICALNEWS": 0, "ANNOUNCEMENT_TYPE": "A", "QUARTER_ID": null, "FILESTATUS": "N    ", "ATTACHMENTNAME": "bc9104ad-c6f4-4f07-b91a-d7f5cdcd8dd0.pdf", "MORE": "Pursuant to Reg 30 and 33 of SEBI (LODR), 2015, we hereby inform you that the Board of Directors at its meeting held today on 30th May, 2024 has inter alia considered and approved Audited Financial Results for the quarter and year ended on 31st March, 2024 along with the Auditors Report for the said period.\r\n\r\nKindly take the same on your records.\r\n", "HEADLINE": "Pursuant to Reg 30 and 33 of SEBI (LODR), 2015, we hereby inform you that the Board of Directors at its meeting held today on 30th May, 2024 has inter alia considered and approved Audited ....", "CATEGORYNAME": "Result", "OLD": 1, "RN": 1, "PDFFLAG": 1, "NSURL": "https://www.bseindia.com/stock-share-price/shah-construction-company-ltd/shahcon/509870/", "SLONGNAME": "Shah Construction Company Ltd", "AGENDA_ID": 30, "TotalPageCnt": 82, "News_submission_dt": "2024-05-30T15:47:23", "DissemDT": "2024-05-30T15:47:23.59", "TimeDiff": "00:00:00", "Fld_Attachsize": 2306236, "SUBCATNAME": "Financial Results", "AUDIO_VIDEO_FILE": null}, {"NEWSID": "e32c8351-9db4-4c40-bf09-5784528231b7", "SCRIP_CD": 500138, "XML_NAME": "ANN_500138_E32C8351-9DB4-4C40-BF09-5784528231B7", "NEWSSUB": "Uniworth Textiles Ltd - 500138 - Outcome Of Board Meeting Dated May 30, 2024", "DT_TM": "2024-05-30 15:46:27.367", "NEWS_DT": "2024-05-30T15:46:27.367", "CRITICALNEWS": 0, "ANNOUNCEMENT_TYPE": "A", "QUARTER_ID": null, "FILESTATUS": "N    ", "ATTACHMENTNAME": "8d959e97-fbda-41b2-8b77-1908e4b80a62.pdf", "MORE": "", "HEADLINE": "Results", "CATEGORYNAME": "Result", "OLD": 1, "RN": 1, "PDFFLAG": 1, "NSURL": "https://www.bseindia.com/stock-share-price/uniworth-textiles-ltd/uniwortht/500138/", "SLONGNAME": "Uniworth Textiles Ltd", "AGENDA_ID": 30, "TotalPageCnt": 82, "News_submission_dt": "2024-05-30T15:46:27", "DissemDT": "2024-05-30T15:46:27.367", "TimeDiff": "00:00:00", "Fld_Attachsize": 10183340, "SUBCATNAME": "Financial Results", "AUDIO_VIDEO_FILE": null}, {"NEWSID": "9a1e7146-5b14-4567-b0c6-98bf975f69b7", "SCRIP_CD": 530745, "XML_NAME": "ANN_530745_9A1E7146-5B14-4567-B0C6-98BF975F69B7", "NEWSSUB": "ACS Technologies Ltd - 530745 - Results - Financial Results For The Quarter And Year Ended 31/03/2024.", "DT_TM": "2024-05-30 15:45:02.243", "NEWS_DT": "2024-05-30T15:45:02.243", "CRITICALNEWS": 0, "ANNOUNCEMENT_TYPE": "A", "QUARTER_ID": null, "FILESTATUS": "N    ", "ATTACHMENTNAME": "4b1ec671-04de-44ba-81c9-6a6eda339fc7.pdf", "MORE": "", "HEADLINE": "Declaration of financial results of the company for the quarter and year ended 31/03/2024.", "CATEGORYNAME": "Result", "OLD": 1, "RN": 1, "PDFFLAG": 1, "NSURL": "https://www.bseindia.com/stock-share-price/acs-technologies-ltd/acstech/530745/", "SLONGNAME": "ACS Technologies Ltd", "AGENDA_ID": 30, "TotalPageCnt": 82, "News_submission_dt": "2024-05-30T15:45:02", "DissemDT": "2024-05-30T15:45:02.243", "TimeDiff": "00:00:00", "Fld_Attachsize": 5626125, "SUBCATNAME": "Financial Results", "AUDIO_VIDEO_FILE": null}, {"NEWSID": "c2bff7ce-1c1c-4109-9347-4cbfe7efc19d", "SCRIP_CD": 506190, "XML_NAME": "ANN_506190_C2BFF7CE-1C1C-4109-9347-4CBFE7EFC19D", "NEWSSUB": "Sarvamangal Mercantile Company Ltd  - 506190 - Results For The Year Ended On March 31, 2024", "DT_TM": "2024-05-30 15:44:39.720", "NEWS_DT": "2024-05-30T15:44:39.72", "CRITICALNEWS": 0, "ANNOUNCEMENT_TYPE": "A", "QUARTER_ID": null, "FILESTATUS": "N    ", "ATTACHMENTNAME": "21cd35f0-eb75-4102-93b9-d1b5a7e53f6e.pdf", "MORE": "", "HEADLINE": "Results for the year ended March 31, 2024", "CATEGORYNAME": "Result", "OLD": 1, "RN": 1, "PDFFLAG": 1, "NSURL": "https://www.bseindia.com/stock-share-price/sarvamangal-mercantile-company-ltd-/zsarvama/506190/", "SLONGNAME": "Sarvamangal Mercantile Company Ltd ", "AGENDA_ID": 30, "TotalPageCnt": 82, "News_submission_dt": "2024-05-30T15:44:39", "DissemDT": "2024-05-30T15:44:39.72", "TimeDiff": "00:00:00", "Fld_Attachsize": 2095580, "SUBCATNAME": "Financial Results", "AUDIO_VIDEO_FILE": null}, {"NEWSID": "1610842b-8d4f-4285-93ca-65409aac0c23", "SCRIP_CD": 531069, "XML_NAME": "ANN_531069_1610842B-8D4F-4285-93CA-65409AAC0C23", "NEWSSUB": "Vijay Solvex Ltd - 531069 - Audited Standalone And Consolidated Financial Results Of The Company For The Quarter And Year Ended March 31, 2024.", "DT_TM": "2024-05-30 15:44:00.737", "NEWS_DT": "2024-05-30T15:44:00.737", "CRITICALNEWS": 0, "ANNOUNCEMENT_TYPE": "A", "QUARTER_ID": null, "FILESTATUS": "N    ", "ATTACHMENTNAME": "e2e79f88-647a-4c13-9a7f-b43535aceed0.pdf", "MORE": "The Board of Directors of the Company in their meeting held on today i.e. 30.05.2024 has, inter alia, considered and approved the Audited Standalone and Consolidated Financial Results of the Company for the quarter and year ended March 31, 2024.", "HEADLINE": "The Board of Directors of the Company in their meeting held on today i.e. 30.05.2024 has, inter alia, considered and approved the Audited Standalone and Consolidated Financial Results of ....", "CATEGORYNAME": "Result", "OLD": 1, "RN": 1, "PDFFLAG": 1, "NSURL": "https://www.bseindia.com/stock-share-price/vijay-solvex-ltd/vijsolx/531069/", "SLONGNAME": "Vijay Solvex Ltd", "AGENDA_ID": 30, "TotalPageCnt": 82, "News_submission_dt": "2024-05-30T15:44:00", "DissemDT": "2024-05-30T15:44:00.737", "TimeDiff": "00:00:00", "Fld_Attachsize": 17253387, "SUBCATNAME": "Financial Results", "AUDIO_VIDEO_FILE": null}, {"NEWSID": "aa2e01bb-57ad-4d13-aa79-a5adabd72a72", "SCRIP_CD": 536710, "XML_NAME": "ANN_536710_AA2E01BB-57AD-4D13-AA79-A5ADABD72A72", "NEWSSUB": "S R G Securities Finance Ltd - 536710 - Results 31-03-2024", "DT_TM": "2024-05-30 15:43:11.393", "NEWS_DT": "2024-05-30T15:43:11.393", "CRITICALNEWS": 0, "ANNOUNCEMENT_TYPE": "A", "QUARTER_ID": null, "FILESTATUS": "N    ", "ATTACHMENTNAME": "b68fd2eb-dd29-43ee-86c9-8fda08a353a8.pdf", "MORE": "", "HEADLINE": "Results 31-03-2024", "CATEGORYNAME": "Result", "OLD": 1, "RN": 1, "PDFFLAG": 1, "NSURL": "https://www.bseindia.com/stock-share-price/s-r-g-securities-finance-ltd/srgsfl/536710/", "SLONGNAME": "S R G Securities Finance Ltd", "AGENDA_ID": 30, "TotalPageCnt": 82, "News_submission_dt": "2024-05-30T15:43:11", "DissemDT": "2024-05-30T15:43:11.393", "TimeDiff": "00:00:00", "Fld_Attachsize": 3444020, "SUBCATNAME": "Financial Results", "AUDIO_VIDEO_FILE": null}, {"NEWSID": "f3f65318-526e-42bf-b4a6-b0fb3a92cae9", "SCRIP_CD": 512377, "XML_NAME": "ANN_512377_F3F65318-526E-42BF-B4A6-B0FB3A92CAE9", "NEWSSUB": "Magnanimous Trade & finance Ltd - 512377 - Results- Results For The Quarter And Year Ended 31St March 2024", "DT_TM": "2024-05-30 15:41:58.700", "NEWS_DT": "2024-05-30T15:41:58.7", "CRITICALNEWS": 0, "ANNOUNCEMENT_TYPE": "A", "QUARTER_ID": null, "FILESTATUS": "N    ", "ATTACHMENTNAME": "f41fa3d1-43cb-4486-be1b-ac2f0a21429e.pdf", "MORE": "", "HEADLINE": "Submission of Audited Standalone and Consolidated financial results for the quarter and year ended 31st March 2024.\r\n", "CATEGORYNAME": "Result", "OLD": 1, "RN": 1, "PDFFLAG": 1, "NSURL": "https://www.bseindia.com/stock-share-price/magnanimous-trade--finance-ltd/magantr/512377/", "SLONGNAME": "Magnanimous Trade & finance Ltd", "AGENDA_ID": 30, "TotalPageCnt": 82, "News_submission_dt": "2024-05-30T15:41:58", "DissemDT": "2024-05-30T15:41:58.7", "TimeDiff": "00:00:00", "Fld_Attachsize": 15198315, "SUBCATNAME": "Financial Results", "AUDIO_VIDEO_FILE": null}, {"NEWSID": "08b6e269-29d2-46eb-84db-4e5269df3ad9", "SCRIP_CD": 526139, "XML_NAME": "ANN_526139_08B6E269-29D2-46EB-84DB-4E5269DF3AD9", "NEWSSUB": "Transgene Biotek Ltd - 526139 - Outcome Of Board Meeting And Submission Of Audited Financial Results For The Financial Year Ended March 31, 2024", "DT_TM": "2024-05-30 15:41:58.610", "NEWS_DT": "2024-05-30T15:41:58.61", "CRITICALNEWS": 0, "ANNOUNCEMENT_TYPE": "A", "QUARTER_ID": null, "FILESTATUS": "N    ", "ATTACHMENTNAME": "f45b2172-fe49-44d1-9958-4ed40fc35e29.pdf", "MORE": "", "HEADLINE": "Audited Results", "CATEGORYNAME": "Result", "OLD": 1, "RN": 1, "PDFFLAG": 1, "NSURL": "https://www.bseindia.com/stock-share-price/transgene-biotek-ltd/trabi/526139/", "SLONGNAME": "Transgene Biotek Ltd", "AGENDA_ID": 30, "TotalPageCnt": 82, "News_submission_dt": "2024-05-30T15:41:58", "DissemDT": "2024-05-30T15:41:58.61", "TimeDiff": "00:00:00", "Fld_Attachsize": 1362026, "SUBCATNAME": "Financial Results", "AUDIO_VIDEO_FILE": null}, {"NEWSID": "b0a23630-7f2d-4a99-bde0-22bcf4889f19", "SCRIP_CD": 544108, "XML_NAME": "ANN_544108_B0A23630-7F2D-4A99-BDE0-22BCF4889F19", "NEWSSUB": "Gabriel Pet Straps Ltd - 544108 - Approval Of Financial Results For The Half Year And Year Ended March 31, 2024", "DT_TM": "2024-05-30 15:40:51.080", "NEWS_DT": "2024-05-30T15:40:51.08", "CRITICALNEWS": 0, "ANNOUNCEMENT_TYPE": "A", "QUARTER_ID": null, "FILESTATUS": "N    ", "ATTACHMENTNAME": "8feab083-ca0e-425d-938f-ee1bd3008808.pdf", "MORE": "", "HEADLINE": "Approval of Financial Results for the Half Year and Year Ended March 31, 2024", "CATEGORYNAME": "Result", "OLD": 1, "RN": 1, "PDFFLAG": 1, "NSURL": "https://www.bseindia.com/stock-share-price/gabriel-pet-straps-ltd/gpsl/544108/", "SLONGNAME": "Gabriel Pet Straps Ltd", "AGENDA_ID": 30, "TotalPageCnt": 82, "News_submission_dt": "2024-05-30T15:40:50", "DissemDT": "2024-05-30T15:40:51.08", "TimeDiff": "00:00:01", "Fld_Attachsize": 1049963, "SUBCATNAME": "Financial Results", "AUDIO_VIDEO_FILE": null}, {"NEWSID": "4917059b-8852-4264-af15-0d570439f092", "SCRIP_CD": 522205, "XML_NAME": "ANN_522205_4917059B-8852-4264-AF15-0D570439F092", "NEWSSUB": "Praj Industries Ltd - 522205 - Audited Financial Results For The Financial Year Ended 31St March 2024", "DT_TM": "2024-05-30 15:40:33.147", "NEWS_DT": "2024-05-30T15:40:33.147", "CRITICALNEWS": 0, "ANNOUNCEMENT_TYPE": "A", "QUARTER_ID": null, "FILESTATUS": "N    ", "ATTACHMENTNAME": "f58cf5d5-d611-44be-847c-29874bab4a9d.pdf", "MORE": "", "HEADLINE": "Audited Financial Results for the financial year ended 31st March 2024", "CATEGORYNAME": "Result", "OLD": 1, "RN": 1, "PDFFLAG": 1, "NSURL": "https://www.bseindia.com/stock-share-price/praj-industries-ltd/prajind/522205/", "SLONGNAME": "Praj Industries Ltd", "AGENDA_ID": 30, "TotalPageCnt": 82, "News_submission_dt": "2024-05-30T15:40:33", "DissemDT": "2024-05-30T15:40:33.147", "TimeDiff": "00:00:00", "Fld_Attachsize": 7344190, "SUBCATNAME": "Financial Results", "AUDIO_VIDEO_FILE": null}, {"NEWSID": "2c66f1b3-9211-4050-a13d-dc360a073142", "SCRIP_CD": 530735, "XML_NAME": "ANN_530735_2C66F1B3-9211-4050-A13D-DC360A073142", "NEWSSUB": "Super Bakers India Ltd - 530735 - Results-Financial Results For March 31, 2024", "DT_TM": "2024-05-30 15:39:20.077", "NEWS_DT": "2024-05-30T15:39:20.077", "CRITICALNEWS": 0, "ANNOUNCEMENT_TYPE": "A", "QUARTER_ID": null, "FILESTATUS": "N    ", "ATTACHMENTNAME": "c29353c9-fdd7-4ff2-8e20-7eb80e120416.pdf", "MORE": "", "HEADLINE": "We are enclosing herewith Audited Financial Results for the year ended on 31st March, 2024 along with Auditors'' Report thereon.", "CATEGORYNAME": "Result", "OLD": 1, "RN": 1, "PDFFLAG": 1, "NSURL": "https://www.bseindia.com/stock-share-price/super-bakers-india-ltd/superbak/530735/", "SLONGNAME": "Super Bakers India Ltd", "AGENDA_ID": 30, "TotalPageCnt": 82, "News_submission_dt": "2024-05-30T15:39:19", "DissemDT": "2024-05-30T15:39:20.077", "TimeDiff": "00:00:01", "Fld_Attachsize": 2888885, "SUBCATNAME": "Financial Results", "AUDIO_VIDEO_FILE": null}, {"NEWSID": "50caf1b1-287c-4830-ab2b-40221e73213b", "SCRIP_CD": 507300, "XML_NAME": "ANN_507300_50CAF1B1-287C-4830-AB2B-40221E73213B", "NEWSSUB": "The Ravalgaon Sugar Farm Ltd - 507300 - Results-Financial Results For March 31, 2024", "DT_TM": "2024-05-30 15:39:16.020", "NEWS_DT": "2024-05-30T15:39:16.02", "CRITICALNEWS": 0, "ANNOUNCEMENT_TYPE": "A", "QUARTER_ID": null, "FILESTATUS": "N    ", "ATTACHMENTNAME": "e0318e11-820d-4de7-add2-d7be3df0d2fb.pdf", "MORE": "", "HEADLINE": "Results-Financial Results for March 31, 2024", "CATEGORYNAME": "Result", "OLD": 1, "RN": 1, "PDFFLAG": 1, "NSURL": "https://www.bseindia.com/stock-share-price/the-ravalgaon-sugar-farm-ltd/ravalsugar/507300/", "SLONGNAME": "The Ravalgaon Sugar Farm Ltd", "AGENDA_ID": 30, "TotalPageCnt": 82, "News_submission_dt": "2024-05-30T15:39:15", "DissemDT": "2024-05-30T15:39:16.02", "TimeDiff": "00:00:01", "Fld_Attachsize": 3666280, "SUBCATNAME": "Financial Results", "AUDIO_VIDEO_FILE": null}, {"NEWSID": "5f0e4d6d-d491-4d20-bb14-946bd8a6c81f", "SCRIP_CD": 500220, "XML_NAME": "ANN_500220_5F0E4D6D-D491-4D20-BB14-946BD8A6C81F", "NEWSSUB": "Jasch Industries Ltd - 500220 - Results - Financial Results For 31-03-2024", "DT_TM": "2024-05-30 15:37:03.660", "NEWS_DT": "2024-05-30T15:37:03.66", "CRITICALNEWS": 0, "ANNOUNCEMENT_TYPE": "A", "QUARTER_ID": null, "FILESTATUS": "N    ", "ATTACHMENTNAME": "6ed9f564-4427-4f49-8909-47f3c73d5841.pdf", "MORE": "", "HEADLINE": "Attached.", "CATEGORYNAME": "Result", "OLD": 1, "RN": 1, "PDFFLAG": 1, "NSURL": "https://www.bseindia.com/stock-share-price/jasch-industries-ltd/jasch/500220/", "SLONGNAME": "Jasch Industries Ltd", "AGENDA_ID": 30, "TotalPageCnt": 82, "News_submission_dt": "2024-05-30T15:37:03", "DissemDT": "2024-05-30T15:37:03.66", "TimeDiff": "00:00:00", "Fld_Attachsize": 13599041, "SUBCATNAME": "Financial Results", "AUDIO_VIDEO_FILE": null}, {"NEWSID": "cecbe60f-cca8-447d-8de3-1a434de83477", "SCRIP_CD": 533168, "XML_NAME": "ANN_533168_CECBE60F-CCA8-447D-8DE3-1A434DE83477", "NEWSSUB": "Rossell India Ltd - 533168 - FINANCIAL RESULTS", "DT_TM": "2024-05-30 15:36:05.713", "NEWS_DT": "2024-05-30T15:36:05.713", "CRITICALNEWS": 0, "ANNOUNCEMENT_TYPE": "A", "QUARTER_ID": null, "FILESTATUS": "N    ", "ATTACHMENTNAME": "75a6974b-d4c7-47d2-9f4e-dbb126d57795.pdf", "MORE": "", "HEADLINE": "As per enclosed Letter", "CATEGORYNAME": "Result", "OLD": 1, "RN": 1, "PDFFLAG": 1, "NSURL": "https://www.bseindia.com/stock-share-price/rossell-india-ltd/rossellind/533168/", "SLONGNAME": "Rossell India Ltd", "AGENDA_ID": 30, "TotalPageCnt": 82, "News_submission_dt": "2024-05-30T15:36:05", "DissemDT": "2024-05-30T15:36:05.713", "TimeDiff": "00:00:00", "Fld_Attachsize": 3491647, "SUBCATNAME": "Financial Results", "AUDIO_VIDEO_FILE": null}, {"NEWSID": "0e92921a-4f43-4bde-b188-f351d20d3ed0", "SCRIP_CD": 506178, "XML_NAME": "ANN_506178_0E92921A-4F43-4BDE-B188-F351D20D3ED0", "NEWSSUB": "Velox Shipping and Logistics Ltd - 506178 - 1) Standalone Audited Financial Results For The Quarter And Year Ended March 31, 2024.\r\n\r\n2) Auditors Report On Standalone Quarterly Financial Results And Financial Results For The Year Ended March 31, 2024", "DT_TM": "2024-05-30 15:35:25.220", "NEWS_DT": "2024-05-30T15:35:25.22", "CRITICALNEWS": 0, "ANNOUNCEMENT_TYPE": "A", "QUARTER_ID": null, "FILESTATUS": "N    ", "ATTACHMENTNAME": "a5db83e6-dfc0-4da9-9046-7a7f3ca3515f.pdf", "MORE": "Approved and taken on records the audited financial results along with auditors report thereon for the quarter and year ended as on March 31, 2024.\r\n\r\nWe hereby confirm and declare that the statutory auditors of the Company M/s. P Shah & Co., Chartered Accountants have issued report with an unmodified opinion in respect of standalone audited financial results for the quarter and year ended as on March 31, 2024.", "HEADLINE": "Approved and taken on records the audited financial results along with auditors report thereon for the quarter and year ended as on March 31, 2024.\r\n\r\nWe hereby confirm and declare that ....", "CATEGORYNAME": "Result", "OLD": 1, "RN": 1, "PDFFLAG": 1, "NSURL": "https://www.bseindia.com/stock-share-price/velox-shipping-and-logistics-ltd/velox/506178/", "SLONGNAME": "Velox Shipping and Logistics Ltd", "AGENDA_ID": 30, "TotalPageCnt": 82, "News_submission_dt": "2024-05-30T15:35:25", "DissemDT": "2024-05-30T15:35:25.22", "TimeDiff": "00:00:00", "Fld_Attachsize": 2632300, "SUBCATNAME": "Financial Results", "AUDIO_VIDEO_FILE": null}, {"NEWSID": "019c9e3c-7faf-4491-b1cd-063471df62ea", "SCRIP_CD": 542753, "XML_NAME": "ANN_542753_019C9E3C-7FAF-4491-B1CD-063471DF62EA", "NEWSSUB": "Seacoast Shipping Services Ltd - 542753 - Results For 31.03.2024", "DT_TM": "2024-05-30 15:35:09.470", "NEWS_DT": "2024-05-30T15:35:09.47", "CRITICALNEWS": 0, "ANNOUNCEMENT_TYPE": "A", "QUARTER_ID": null, "FILESTATUS": "N    ", "ATTACHMENTNAME": "740f3203-18d5-4a09-b1a9-4a13ea69a426.pdf", "MORE": "", "HEADLINE": "Results", "CATEGORYNAME": "Result", "OLD": 1, "RN": 1, "PDFFLAG": 1, "NSURL": "https://www.bseindia.com/stock-share-price/seacoast-shipping-services-ltd/seacoast/542753/", "SLONGNAME": "Seacoast Shipping Services Ltd", "AGENDA_ID": 30, "TotalPageCnt": 82, "News_submission_dt": "2024-05-30T15:35:09", "DissemDT": "2024-05-30T15:35:09.47", "TimeDiff": "00:00:00", "Fld_Attachsize": 3677246, "SUBCATNAME": "Financial Results", "AUDIO_VIDEO_FILE": null}, {"NEWSID": "8763d155-b14b-4223-8082-a8ec161e96be", "SCRIP_CD": 530973, "XML_NAME": "ANN_530973_8763D155-B14B-4223-8082-A8EC161E96BE", "NEWSSUB": "Alfa Ica India Ltd - 530973 - Results- Audited Financial Results For Year Ended March 31,2024", "DT_TM": "2024-05-30 15:34:27.250", "NEWS_DT": "2024-05-30T15:34:27.25", "CRITICALNEWS": 0, "ANNOUNCEMENT_TYPE": "A", "QUARTER_ID": null, "FILESTATUS": "N    ", "ATTACHMENTNAME": "efde6eb2-7d3c-4116-9145-c809e9904857.pdf", "MORE": "", "HEADLINE": "Outcome of board meeting", "CATEGORYNAME": "Result", "OLD": 1, "RN": 1, "PDFFLAG": 1, "NSURL": "https://www.bseindia.com/stock-share-price/alfa-ica-india-ltd/alfaica/530973/", "SLONGNAME": "Alfa Ica India Ltd", "AGENDA_ID": 30, "TotalPageCnt": 82, "News_submission_dt": "2024-05-30T15:34:27", "DissemDT": "2024-05-30T15:34:27.25", "TimeDiff": "00:00:00", "Fld_Attachsize": 5199677, "SUBCATNAME": "Financial Results", "AUDIO_VIDEO_FILE": null}, {"NEWSID": "509fb000-fed9-42de-a073-45f735217f26", "SCRIP_CD": 504998, "XML_NAME": "ANN_504998_509FB000-FED9-42DE-A073-45F735217F26", "NEWSSUB": "Western Ministil Ltd - 504998 - Financial Results For March 31, 2024", "DT_TM": "2024-05-30 15:33:45.743", "NEWS_DT": "2024-05-30T15:33:45.743", "CRITICALNEWS": 0, "ANNOUNCEMENT_TYPE": "A", "QUARTER_ID": null, "FILESTATUS": "N    ", "ATTACHMENTNAME": "f0b2b75a-1359-4619-af09-0a93882e19dd.pdf", "MORE": "", "HEADLINE": "Please find attached Audited Financial Results for the quarter and year ended March 31, 2024.", "CATEGORYNAME": "Result", "OLD": 1, "RN": 1, "PDFFLAG": 1, "NSURL": "https://www.bseindia.com/stock-share-price/western-ministil-ltd/wminimt/504998/", "SLONGNAME": "Western Ministil Ltd", "AGENDA_ID": 30, "TotalPageCnt": 82, "News_submission_dt": "2024-05-30T15:33:45", "DissemDT": "2024-05-30T15:33:45.743", "TimeDiff": "00:00:00", "Fld_Attachsize": 9445571, "SUBCATNAME": "Financial Results", "AUDIO_VIDEO_FILE": null}, {"NEWSID": "e585c38c-03b3-44fc-95fc-bfcb1adf2f5d", "SCRIP_CD": 538837, "XML_NAME": "ANN_538837_E585C38C-03B3-44FC-95FC-BFCB1ADF2F5D", "NEWSSUB": "Jeevan Scientific Technology Ltd - 538837 - Audited Financial Results (Standalone And Consolidated) For The Quarter And Financial Year Ended 31.03.2024", "DT_TM": "2024-05-30 15:26:30.810", "NEWS_DT": "2024-05-30T15:26:30.81", "CRITICALNEWS": 0, "ANNOUNCEMENT_TYPE": "A", "QUARTER_ID": null, "FILESTATUS": "N    ", "ATTACHMENTNAME": "d2505c6d-697a-4e9d-9f0d-dd2390a43919.pdf", "MORE": "", "HEADLINE": "Audited financial results ( Standalone and Consolidated) for the quarter and financial year ended 31.03.2024", "CATEGORYNAME": "Result", "OLD": 1, "RN": 1, "PDFFLAG": 1, "NSURL": "https://www.bseindia.com/stock-share-price/jeevan-scientific-technology-ltd/jstl/538837/", "SLONGNAME": "Jeevan Scientific Technology Ltd", "AGENDA_ID": 30, "TotalPageCnt": 82, "News_submission_dt": "2024-05-30T15:26:30", "DissemDT": "2024-05-30T15:26:30.81", "TimeDiff": "00:00:00", "Fld_Attachsize": 14313379, "SUBCATNAME": "Financial Results", "AUDIO_VIDEO_FILE": null}, {"NEWSID": "09718fe2-3482-41a5-a9f6-d9f27a300cd6", "SCRIP_CD": 530565, "XML_NAME": "ANN_530565_09718FE2-3482-41A5-A9F6-D9F27A300CD6", "NEWSSUB": "Popees Cares Ltd - 530565 - Financial Results For The Year Ended 31.03.2024", "DT_TM": "2024-05-30 15:26:16.810", "NEWS_DT": "2024-05-30T15:26:16.81", "CRITICALNEWS": 0, "ANNOUNCEMENT_TYPE": "A", "QUARTER_ID": null, "FILESTATUS": "N    ", "ATTACHMENTNAME": "1aca7f77-a5c3-4525-b554-351f1986df3f.pdf", "MORE": "", "HEADLINE": "Submission of Audited Standalone Financial Results of the company for the Financial Year 2023-2024.", "CATEGORYNAME": "Result", "OLD": 1, "RN": 1, "PDFFLAG": 1, "NSURL": "https://www.bseindia.com/stock-share-price/popees-cares-ltd/popees/530565/", "SLONGNAME": "Popees Cares Ltd", "AGENDA_ID": 30, "TotalPageCnt": 82, "News_submission_dt": "2024-05-30T15:26:16", "DissemDT": "2024-05-30T15:26:16.81", "TimeDiff": "00:00:00", "Fld_Attachsize": 4102656, "SUBCATNAME": "Financial Results", "AUDIO_VIDEO_FILE": null}, {"NEWSID": "8a7f2998-7853-4c0f-ab49-a6c1b179f417", "SCRIP_CD": 536073, "XML_NAME": "ANN_536073_8A7F2998-7853-4C0F-AB49-A6C1B179F417", "NEWSSUB": "Julien Agro Infratech Ltd - 536073 - Submission Of Audited Financial Results Pursuant To Regulation 33 Of SEBI (Listing Obligations & Disclosure Requirements) Regulations, 2015 For The Fourth Quarter And Financial Year Ended March 31, 2024", "DT_TM": "2024-05-30 15:24:44.247", "NEWS_DT": "2024-05-30T15:24:44.247", "CRITICALNEWS": 0, "ANNOUNCEMENT_TYPE": "A", "QUARTER_ID": null, "FILESTATUS": "N    ", "ATTACHMENTNAME": "a9109db8-6957-46f4-aa16-2435b76a20d9.pdf", "MORE": "", "HEADLINE": "With reference to above mentioned subject please find the enclosed herewith audited financial result for the year ended March 31, 2024.", "CATEGORYNAME": "Result", "OLD": 1, "RN": 1, "PDFFLAG": 1, "NSURL": "https://www.bseindia.com/stock-share-price/julien-agro-infratech-ltd/julien/536073/", "SLONGNAME": "Julien Agro Infratech Ltd", "AGENDA_ID": 30, "TotalPageCnt": 82, "News_submission_dt": "2024-05-30T15:24:44", "DissemDT": "2024-05-30T15:24:44.247", "TimeDiff": "00:00:00", "Fld_Attachsize": 2037186, "SUBCATNAME": "Financial Results", "AUDIO_VIDEO_FILE": null}, {"NEWSID": "9e157487-970e-4301-8c1e-b28107c55a79", "SCRIP_CD": 530179, "XML_NAME": "ANN_530179_9E157487-970E-4301-8C1E-B28107C55A79", "NEWSSUB": "RSC International Ltd - 530179 - Result : Financial Result For The Period Ended 31St March 2024", "DT_TM": "2024-05-30 15:24:08.187", "NEWS_DT": "2024-05-30T15:24:08.187", "CRITICALNEWS": 0, "ANNOUNCEMENT_TYPE": "A", "QUARTER_ID": null, "FILESTATUS": "N    ", "ATTACHMENTNAME": "f57cde4b-7c65-47e8-9bb9-9927f1acc354.pdf", "MORE": "", "HEADLINE": "This is to inform that the Board has considered and approved the Audited financials result for the Quarter/year ended 31st March 2024", "CATEGORYNAME": "Result", "OLD": 1, "RN": 1, "PDFFLAG": 1, "NSURL": "https://www.bseindia.com/stock-share-price/rsc-international-ltd/rscint/530179/", "SLONGNAME": "RSC International Ltd", "AGENDA_ID": 30, "TotalPageCnt": 82, "News_submission_dt": "2024-05-30T15:24:08", "DissemDT": "2024-05-30T15:24:08.187", "TimeDiff": "00:00:00", "Fld_Attachsize": 3491468, "SUBCATNAME": "Financial Results", "AUDIO_VIDEO_FILE": null}, {"NEWSID": "1e8b0ae6-07c4-4edc-8ec4-56de2e3efc36", "SCRIP_CD": 531471, "XML_NAME": "ANN_531471_1E8B0AE6-07C4-4EDC-8EC4-56DE2E3EFC36", "NEWSSUB": "Duke Offshore Ltd - 531471 - RESULT FOR THE QUARTER AND YEAR ENDED ON 31/03/2024", "DT_TM": "2024-05-30 15:23:52.130", "NEWS_DT": "2024-05-30T15:23:52.13", "CRITICALNEWS": 0, "ANNOUNCEMENT_TYPE": "A", "QUARTER_ID": null, "FILESTATUS": "N    ", "ATTACHMENTNAME": "5a65fb5b-cced-4ad8-b7f4-2b298613ec68.pdf", "MORE": "", "HEADLINE": "AUDITED RESULT FOR THE YEAR ENDED ON 31/03/2024", "CATEGORYNAME": "Result", "OLD": 1, "RN": 1, "PDFFLAG": 1, "NSURL": "https://www.bseindia.com/stock-share-price/duke-offshore-ltd/dukeofs/531471/", "SLONGNAME": "Duke Offshore Ltd", "AGENDA_ID": 30, "TotalPageCnt": 82, "News_submission_dt": "2024-05-30T15:23:51", "DissemDT": "2024-05-30T15:23:52.13", "TimeDiff": "00:00:01", "Fld_Attachsize": 1587523, "SUBCATNAME": "Financial Results", "AUDIO_VIDEO_FILE": null}, {"NEWSID": "9199612c-b62f-4f0f-97ff-9d6351df989b", "SCRIP_CD": 503657, "XML_NAME": "ANN_503657_9199612C-B62F-4F0F-97FF-9D6351DF989B", "NEWSSUB": "Veer Energy & Infrastructure Ltd - 503657 - Results-Financial Results For March 31, 2024", "DT_TM": "2024-05-30 15:22:54.660", "NEWS_DT": "2024-05-30T15:22:54.66", "CRITICALNEWS": 0, "ANNOUNCEMENT_TYPE": "A", "QUARTER_ID": null, "FILESTATUS": "N    ", "ATTACHMENTNAME": "7a809348-4387-4072-85f1-8ad948850c3b.pdf", "MORE": "", "HEADLINE": "Please find attached Audited Financial Results for the quarter and year ended 31st March, 2024.", "CATEGORYNAME": "Result", "OLD": 1, "RN": 1, "PDFFLAG": 1, "NSURL": "https://www.bseindia.com/stock-share-price/veer-energy--infrastructure-ltd/veerenrgy/503657/", "SLONGNAME": "Veer Energy & Infrastructure Ltd", "AGENDA_ID": 30, "TotalPageCnt": 82, "News_submission_dt": "2024-05-30T15:22:54", "DissemDT": "2024-05-30T15:22:54.66", "TimeDiff": "00:00:00", "Fld_Attachsize": 3280243, "SUBCATNAME": "Financial Results", "AUDIO_VIDEO_FILE": null}, {"NEWSID": "85bdbaa8-94db-485a-b445-30f9b6db3efc", "SCRIP_CD": 543843, "XML_NAME": "ANN_543843_85BDBAA8-94DB-485A-B445-30F9B6DB3EFC", "NEWSSUB": "Command Polymers Ltd - 543843 - Results- Financial Year Ended 31.03.2024", "DT_TM": "2024-05-30 15:21:24.907", "NEWS_DT": "2024-05-30T15:21:24.907", "CRITICALNEWS": 0, "ANNOUNCEMENT_TYPE": "A", "QUARTER_ID": null, "FILESTATUS": "N    ", "ATTACHMENTNAME": "7d0603f6-ac2e-482b-975d-f6fec48825ca.pdf", "MORE": "", "HEADLINE": "Kindly take the same on records.", "CATEGORYNAME": "Result", "OLD": 1, "RN": 1, "PDFFLAG": 1, "NSURL": "https://www.bseindia.com/stock-share-price/command-polymers-ltd/command/543843/", "SLONGNAME": "Command Polymers Ltd", "AGENDA_ID": 30, "TotalPageCnt": 82, "News_submission_dt": "2024-05-30T15:21:24", "DissemDT": "2024-05-30T15:21:24.907", "TimeDiff": "00:00:00", "Fld_Attachsize": 15259676, "SUBCATNAME": "Financial Results", "AUDIO_VIDEO_FILE": null}, {"NEWSID": "cfa2f9da-2964-407c-bfd7-2781ee6dc5b9", "SCRIP_CD": 530231, "XML_NAME": "ANN_530231_CFA2F9DA-2964-407C-BFD7-2781EE6DC5B9", "NEWSSUB": "Subhash Silk Mills Ltd - 530231 - Submission Of Audited Financial Results And Report Of The Auditors As Per Regulation 33 Of SEBI (Listing Obligations And Disclosures Requirements), Regulations 2015 For The Quarter And Year Ended March 31, 2024", "DT_TM": "2024-05-30 15:20:11.300", "NEWS_DT": "2024-05-30T15:20:11.3", "CRITICALNEWS": 0, "ANNOUNCEMENT_TYPE": "A", "QUARTER_ID": null, "FILESTATUS": "N    ", "ATTACHMENTNAME": "293edef3-6511-4406-ac83-e5b0a1ba576d.pdf", "MORE": "The Board of Directors of the Company at their meeting held on Thursday, May 30, 2024 have duly approved the Audited Financial Results for the quarter and year ended March 31, 2024, together with the Report of the Auditors in terms of Regulation 33 of SEBI (Listing Obligations and Disclosure Requirements) Regulations 2015. \r\n\r\nWe are thus enclosing the Audited Financial Results for the quarter and year ended March 31, 2024, together with the Report of the Auditors in terms of Regulation 33 of SEBI (Listing Obligations and Disclosure Requirements) Regulations 2015.\r\n\r\nThe Board Meeting of the Company commenced on 2.05 pm (IST) and concluded at 2.45 pm (IST).\r\n\r\nThe abovementioned financial results and disclosure shall be available on website of the Company at https://www.subhashsilkmills.com/investor-relations/subhash-silk-mills-invstor-relations.htm . \r\n\r\nYou are requested to take the same on your record.", "HEADLINE": "The Board of Directors of the Company at their meeting held on Thursday, May 30, 2024 have duly approved the Audited Financial Results for the quarter and year ended March 31, 2024, together ....", "CATEGORYNAME": "Result", "OLD": 1, "RN": 1, "PDFFLAG": 1, "NSURL": "https://www.bseindia.com/stock-share-price/subhash-silk-mills-ltd/subsm/530231/", "SLONGNAME": "Subhash Silk Mills Ltd", "AGENDA_ID": 30, "TotalPageCnt": 82, "News_submission_dt": "2024-05-30T15:20:11", "DissemDT": "2024-05-30T15:20:11.3", "TimeDiff": "00:00:00", "Fld_Attachsize": 923673, "SUBCATNAME": "Financial Results", "AUDIO_VIDEO_FILE": null}, {"NEWSID": "ddac71ad-0632-45f3-8bfb-0a5e26f50891", "SCRIP_CD": 539593, "XML_NAME": "ANN_539593_DDAC71AD-0632-45F3-8BFB-0A5E26F50891", "NEWSSUB": "Shivansh Finserve Ltd - 539593 - Financial Results For The Quarter And Year Ended 31St March 2024", "DT_TM": "2024-05-30 15:20:06.393", "NEWS_DT": "2024-05-30T15:20:06.393", "CRITICALNEWS": 0, "ANNOUNCEMENT_TYPE": "A", "QUARTER_ID": null, "FILESTATUS": "N    ", "ATTACHMENTNAME": "c30b26fc-0453-47a9-8762-b428e9fa92b3.pdf", "MORE": "The board meeting was held today to approve the consolidated and standalone audited financial results for the quarter and year ended 31st March, 2024.\r\n\r\nThe meeting commenced at 02:00 pm and concluded at 03:00 pm", "HEADLINE": "The board meeting was held today to approve the consolidated and standalone audited financial results for the quarter and year ended 31st March, 2024.\r\n\r\nThe meeting commenced at 02:00 ....", "CATEGORYNAME": "Result", "OLD": 1, "RN": 1, "PDFFLAG": 1, "NSURL": "https://www.bseindia.com/stock-share-price/shivansh-finserve-ltd/shiva/539593/", "SLONGNAME": "Shivansh Finserve Ltd", "AGENDA_ID": 30, "TotalPageCnt": 82, "News_submission_dt": "2024-05-30T15:20:06", "DissemDT": "2024-05-30T15:20:06.393", "TimeDiff": "00:00:00", "Fld_Attachsize": 5877182, "SUBCATNAME": "Financial Results", "AUDIO_VIDEO_FILE": null}]}